stravacookies/__init__.py
stravacookies/browser.py
stravacookies/fetch_error.py
stravacookies/fetcher.py
stravacookies-1.3.dist-info/LICENSE
stravacookies-1.3.dist-info/METADATA
stravacookies-1.3.dist-info/WHEEL
stravacookies-1.3.dist-info/top_level.txt
stravacookies-1.3.dist-info/RECORD
