Metadata-Version: 2.1
Name: stravacookies
Version: 1.3
Summary: A small package providing methods for retrieving Strava's HTTP cookies needed to download Strava's global heatmap in high resolution.
Home-page: https://github.com/solitone/stravacookies
Author: solitone
Author-email: solitone@mail.com
Project-URL: Bug Tracker, https://github.com/solitone/stravacookies/issues
Classifier: Programming Language :: Python :: 3
Classifier: License :: OSI Approved :: GNU General Public License v3 (GPLv3)
Classifier: Operating System :: OS Independent
Requires-Python: >=3.6
License-File: LICENSE
Requires-Dist: mechanize
